scikit_learnt/__init__.py
scikit_learnt/core.py
scikit_learnt-0.1.1.dist-info/METADATA
scikit_learnt-0.1.1.dist-info/WHEEL
scikit_learnt-0.1.1.dist-info/top_level.txt
scikit_learnt-0.1.1.dist-info/RECORD
