Metadata-Version: 2.1
Name: scikit_learnt
Version: 0.1.1
Home-page: https://github.com/username/scikit_learns
Author: Shaheer
Author-email: shaheerzk01@gmail.com
Classifier: Programming Language :: Python :: 3
Classifier: License :: OSI Approved :: MIT License
Classifier: Operating System :: OS Independent
Requires-Python: >=3.6
Requires-Dist: openai ==0.28.0
